<?xml version="1.0" encoding="utf-8"?>
<cScenarioProperties xmlns:d="http://www.kuju.com/TnT/2003/Delta" d:version="1.0" d:id="264014550">
	<ID>
		<cGUID>
			<UUID>
				<e d:type="sUInt64">4813828859054713691</e>
				<e d:type="sUInt64">1184641147553554099</e>
			</UUID>
			<DevString d:type="cDeltaString">b17aeb5b-27d7-42ce-b39e-3de2d8b07010</DevString>
		</cGUID>
	</ID>
	<String/>
	<DisplayName>
		<Localisation-cUserLocalisedString>
			<English d:type="cDeltaString">R116 Telč - Třebíč 8:00 22.3.2022</English>
			<French d:type="cDeltaString"></French>
			<Italian d:type="cDeltaString"></Italian>
			<German d:type="cDeltaString"></German>
			<Spanish d:type="cDeltaString"></Spanish>
			<Dutch d:type="cDeltaString"></Dutch>
			<Polish d:type="cDeltaString"></Polish>
			<Russian d:type="cDeltaString"></Russian>
			<Other/>
			<Key d:type="cDeltaString">e68ddcc7-f62c-497e-947d-f1809808de6f</Key>
		</Localisation-cUserLocalisedString>
	</DisplayName>
	<Description>
		<Localisation-cUserLocalisedString>
			<English d:type="cDeltaString">&lt;supply description&gt;</English>
			<French d:type="cDeltaString"></French>
			<Italian d:type="cDeltaString"></Italian>
			<German d:type="cDeltaString"></German>
			<Spanish d:type="cDeltaString"></Spanish>
			<Dutch d:type="cDeltaString"></Dutch>
			<Polish d:type="cDeltaString"></Polish>
			<Russian d:type="cDeltaString"></Russian>
			<Other/>
			<Key d:type="cDeltaString">819e9b3d-793d-4c2f-b909-ee45fb3e03a3</Key>
		</Localisation-cUserLocalisedString>
	</Description>
	<Briefing>
		<Localisation-cUserLocalisedString>
			<English d:type="cDeltaString">&lt;supply briefing&gt;</English>
			<French d:type="cDeltaString"></French>
			<Italian d:type="cDeltaString"></Italian>
			<German d:type="cDeltaString"></German>
			<Spanish d:type="cDeltaString"></Spanish>
			<Dutch d:type="cDeltaString"></Dutch>
			<Polish d:type="cDeltaString"></Polish>
			<Russian d:type="cDeltaString"></Russian>
			<Other/>
			<Key d:type="cDeltaString">59b34dc9-1f99-4c76-a749-6d174eaab76c</Key>
		</Localisation-cUserLocalisedString>
	</Briefing>
	<StartLocation>
		<Localisation-cUserLocalisedString>
			<English d:type="cDeltaString"></English>
			<French d:type="cDeltaString"></French>
			<Italian d:type="cDeltaString"></Italian>
			<German d:type="cDeltaString"></German>
			<Spanish d:type="cDeltaString"></Spanish>
			<Dutch d:type="cDeltaString"></Dutch>
			<Polish d:type="cDeltaString"></Polish>
			<Russian d:type="cDeltaString"></Russian>
			<Other/>
			<Key d:type="cDeltaString">d51490bc-04ad-4723-b039-8a48adcebbf2</Key>
		</Localisation-cUserLocalisedString>
	</StartLocation>
	<ScenarioClass d:type="cDeltaString">eStandardScenarioClass</ScenarioClass>
	<StartTime d:type="sFloat32" d:alt_encoding="000000000002DC40" d:precision="string">28680</StartTime>
	<DurationMins d:type="sInt32">20</DurationMins>
	<StartDD d:type="sInt32">22</StartDD>
	<StartMM d:type="sInt32">3</StartMM>
	<StartYYYY d:type="sInt32">2022</StartYYYY>
	<Season d:type="cDeltaString">SEASON_WINTER</Season>
	<WeatherBlueprint>
		<iBlueprintLibrary-cAbsoluteBlueprintID>
			<BlueprintSetID>
				<iBlueprintLibrary-cBlueprintSetID>
					<Provider d:type="cDeltaString">CS_addon</Provider>
					<Product d:type="cDeltaString">Hekl</Product>
				</iBlueprintLibrary-cBlueprintSetID>
			</BlueprintSetID>
			<BlueprintID d:type="cDeltaString">Weather\blueprint\CS_3D_Zatazeno.xml</BlueprintID>
		</iBlueprintLibrary-cAbsoluteBlueprintID>
	</WeatherBlueprint>
	<WeatherExtensionBlueprint>
		<iBlueprintLibrary-cAbsoluteBlueprintID>
			<BlueprintSetID>
				<iBlueprintLibrary-cBlueprintSetID>
					<Provider d:type="cDeltaString"></Provider>
					<Product d:type="cDeltaString"></Product>
				</iBlueprintLibrary-cBlueprintSetID>
			</BlueprintSetID>
			<BlueprintID d:type="cDeltaString"></BlueprintID>
		</iBlueprintLibrary-cAbsoluteBlueprintID>
	</WeatherExtensionBlueprint>
	<Rating d:type="sInt32">5</Rating>
	<LocoClass d:type="cDeltaString">LOCO_NO_CLASS</LocoClass>
	<HasRollingStart d:type="bool">0</HasRollingStart>
	<LoadedFromRollingStart d:type="bool">0</LoadedFromRollingStart>
	<FrontEndDriverList>
		<sDriverFrontEndDetails d:id="286577172">
			<ServiceName>
				<Localisation-cUserLocalisedString>
					<English d:type="cDeltaString">Service1</English>
					<French d:type="cDeltaString"></French>
					<Italian d:type="cDeltaString"></Italian>
					<German d:type="cDeltaString"></German>
					<Spanish d:type="cDeltaString"></Spanish>
					<Dutch d:type="cDeltaString"></Dutch>
					<Polish d:type="cDeltaString"></Polish>
					<Russian d:type="cDeltaString"></Russian>
					<Other/>
					<Key d:type="cDeltaString">b987dbcb-6fe9-4454-8da1-b64bea6c1957</Key>
				</Localisation-cUserLocalisedString>
			</ServiceName>
			<LocoName>
				<Localisation-cUserLocalisedString>
					<English d:type="cDeltaString">OEBB 1216 025 World Record</English>
					<French d:type="cDeltaString">OEBB 1216 025 World Record</French>
					<Italian d:type="cDeltaString">OEBB 1216 025 World Record</Italian>
					<German d:type="cDeltaString">ÖBB 1216 025 World Record</German>
					<Spanish d:type="cDeltaString">OEBB 1216 025 World Record</Spanish>
					<Dutch d:type="cDeltaString">OEBB 1216 025 World Record</Dutch>
					<Polish d:type="cDeltaString">OEBB 1216 025 World Record</Polish>
					<Russian d:type="cDeltaString">OEBB 1216 025 World Record</Russian>
					<Other/>
					<Key d:type="cDeltaString">cf80434c-113c-4754-ac0c-93a45d7e2894</Key>
				</Localisation-cUserLocalisedString>
			</LocoName>
			<LocoBP>
				<iBlueprintLibrary-cAbsoluteBlueprintID>
					<BlueprintSetID>
						<iBlueprintLibrary-cBlueprintSetID>
							<Provider d:type="cDeltaString">RWAustria_2</Provider>
							<Product d:type="cDeltaString">OEBB_1216</Product>
						</iBlueprintLibrary-cBlueprintSetID>
					</BlueprintSetID>
					<BlueprintID d:type="cDeltaString">Electric\1216_0xx\1216_Record\OEBB_1216_0xx_.xml</BlueprintID>
				</iBlueprintLibrary-cAbsoluteBlueprintID>
			</LocoBP>
			<StartLocation>
				<Localisation-cUserLocalisedString>
					<English d:type="cDeltaString">Telč 2/3</English>
					<French d:type="cDeltaString"></French>
					<Italian d:type="cDeltaString"></Italian>
					<German d:type="cDeltaString"></German>
					<Spanish d:type="cDeltaString"></Spanish>
					<Dutch d:type="cDeltaString"></Dutch>
					<Polish d:type="cDeltaString"></Polish>
					<Russian d:type="cDeltaString"></Russian>
					<Other/>
					<Key d:type="cDeltaString">c0898f05-dec1-44ad-b41c-b38a77866856</Key>
				</Localisation-cUserLocalisedString>
			</StartLocation>
			<LocoClass d:type="cDeltaString">LOCO_CLASS_ELECTRIC</LocoClass>
			<LocoAuthor d:type="cDeltaString">RWAustria_2</LocoAuthor>
			<FilePath d:type="cDeltaString">RWAustria_2\OEBB_1216\Electric\1216_0xx\1216_Record</FilePath>
			<Longitude d:type="sFloat64" d:alt_encoding="E42EB3B78FED2E40" d:precision="string">15.464</Longitude>
			<Latitude d:type="sFloat64" d:alt_encoding="7D109EE720974840" d:precision="string">49.1807</Latitude>
			<Height d:type="sFloat32" d:alt_encoding="00000060E2788040" d:precision="string">527.111</Height>
			<PlayerDriver d:type="bool">1</PlayerDriver>
		</sDriverFrontEndDetails>
	</FrontEndDriverList>
	<RequiredSet>
		<iBlueprintLibrary-cBlueprintSetID d:id="312397436">
			<Provider d:type="cDeltaString">RWAustria</Provider>
			<Product d:type="cDeltaString">Austria_RailVehicles</Product>
		</iBlueprintLibrary-cBlueprintSetID>
		<iBlueprintLibrary-cBlueprintSetID d:id="312397438">
			<Provider d:type="cDeltaString">RWAustria_2</Provider>
			<Product d:type="cDeltaString">OEBB_1216</Product>
		</iBlueprintLibrary-cBlueprintSetID>
	</RequiredSet>
	<Gizmo>
		<cOwnedEntity d:id="58136764">
			<Component>
				<cEditorSceneryRender d:id="264018740">
					<DetailLevel d:type="sInt32">10</DetailLevel>
					<Global d:type="bool">0</Global>
					<Saved d:type="bool">1</Saved>
					<Palette0Index d:type="sUInt8">0</Palette0Index>
					<Palette1Index d:type="sUInt8">0</Palette1Index>
					<Palette2Index d:type="sUInt8">0</Palette2Index>
				</cEditorSceneryRender>
				<cPosOri d:id="264019500">
					<Scale d:numElements="4" d:elementType="sFloat32" d:precision="string">1.0000000 1.0000000 1.0000000 0.0000000</Scale>
					<RFarMatrix>
						<cFarMatrix d:id="264019506">
							<Height d:type="sFloat32" d:alt_encoding="000000E0227A8040" d:precision="string">527.267</Height>
							<RXAxis d:numElements="4" d:elementType="sFloat32" d:precision="string">1.0000000 0.0000000 0.0000000 0.0000000</RXAxis>
							<RYAxis d:numElements="4" d:elementType="sFloat32" d:precision="string">0.0000000 1.0000000 0.0000000 0.0000000</RYAxis>
							<RZAxis d:numElements="4" d:elementType="sFloat32" d:precision="string">0.0000000 0.0000000 1.0000000 0.0000000</RZAxis>
							<RFarPosition>
								<cFarVector2 d:id="264019513">
									<X>
										<cFarCoordinate>
											<RouteCoordinate>
												<cRouteCoordinate>
													<Distance d:type="sInt32">-30</Distance>
												</cRouteCoordinate>
											</RouteCoordinate>
											<TileCoordinate>
												<cTileCoordinate>
													<Distance d:type="sFloat32" d:alt_encoding="000000E0A7587C40" d:precision="string">453.541</Distance>
												</cTileCoordinate>
											</TileCoordinate>
										</cFarCoordinate>
									</X>
									<Z>
										<cFarCoordinate>
											<RouteCoordinate>
												<cRouteCoordinate>
													<Distance d:type="sInt32">-5</Distance>
												</cRouteCoordinate>
											</RouteCoordinate>
											<TileCoordinate>
												<cTileCoordinate>
													<Distance d:type="sFloat32" d:alt_encoding="000000E07A1F8C40" d:precision="string">899.935</Distance>
												</cTileCoordinate>
											</TileCoordinate>
										</cFarCoordinate>
									</Z>
								</cFarVector2>
							</RFarPosition>
						</cFarMatrix>
					</RFarMatrix>
				</cPosOri>
				<cScriptComponent d:id="264022334">
					<DebugDisplay d:type="bool">1</DebugDisplay>
					<StateName d:type="cDeltaString"></StateName>
				</cScriptComponent>
			</Component>
			<BlueprintID>
				<iBlueprintLibrary-cAbsoluteBlueprintID>
					<BlueprintSetID>
						<iBlueprintLibrary-cBlueprintSetID>
							<Provider d:type="cDeltaString">Kuju</Provider>
							<Product d:type="cDeltaString">RailSimulatorCore</Product>
						</iBlueprintLibrary-cBlueprintSetID>
					</BlueprintSetID>
					<BlueprintID d:type="cDeltaString">Editor\Gizmo\Scenario Markers\Standard Scenario Marker.xml</BlueprintID>
				</iBlueprintLibrary-cAbsoluteBlueprintID>
			</BlueprintID>
			<ReskinBlueprintID>
				<iBlueprintLibrary-cAbsoluteBlueprintID>
					<BlueprintSetID>
						<iBlueprintLibrary-cBlueprintSetID>
							<Provider d:type="cDeltaString"></Provider>
							<Product d:type="cDeltaString"></Product>
						</iBlueprintLibrary-cBlueprintSetID>
					</BlueprintSetID>
					<BlueprintID d:type="cDeltaString"></BlueprintID>
				</iBlueprintLibrary-cAbsoluteBlueprintID>
			</ReskinBlueprintID>
			<Name d:type="cDeltaString">Standard Scenario Marker</Name>
			<EntityID>
				<cGUID>
					<UUID>
						<e d:type="sUInt64">5279867117393699998</e>
						<e d:type="sUInt64">1792550266863093431</e>
					</UUID>
					<DevString d:type="cDeltaString">5984649e-db2b-4945-b706-686af86ae018</DevString>
				</cGUID>
			</EntityID>
		</cOwnedEntity>
	</Gizmo>
	<SimulationTime d:type="sFloat32" d:alt_encoding="0000000000000000" d:precision="string">0</SimulationTime>
	<AuthoredLanguage d:type="cDeltaString">en</AuthoredLanguage>
	<Version d:type="sFloat32" d:alt_encoding="000000000000F03F" d:precision="string">1</Version>
	<Author d:type="cDeltaString"></Author>
	<DispatcherVersion d:type="cDeltaString">V1</DispatcherVersion>
	<RBlueprintSetPreLoad/>
	<NamedEntity/>
	<Condition/>
	<DeferredEvent/>
	<CheckedCondition/>
	<CareerRules>
		<d:nil/>
	</CareerRules>
	<MD5 d:type="cDeltaString">F80B241C3E6D746C0E43E40E279FA6C0</MD5>
	<MessageEvent/>
	<SimpleControlsOnly d:type="bool">0</SimpleControlsOnly>
	<ExpertControlsOnly d:type="bool">0</ExpertControlsOnly>
	<LocksScenario/>
	<StartDestString/>
	<TemplateStartDestMapping/>
	<IsTemplateGenerated d:type="bool">0</IsTemplateGenerated>
	<TemplateScenarioGUID>
		<cGUID>
			<UUID>
				<e d:type="sUInt64">0</e>
				<e d:type="sUInt64">0</e>
			</UUID>
			<DevString d:type="cDeltaString">00000000-0000-0000-0000-000000000000</DevString>
		</cGUID>
	</TemplateScenarioGUID>
	<WorkshopId d:type="sUInt64">0</WorkshopId>
	<WorkshopBy d:type="sUInt64">0</WorkshopBy>
	<WorkshopTags d:type="cDeltaString"></WorkshopTags>
	<StartInCab d:type="bool">0</StartInCab>
	<IsClonedDLC d:type="bool">0</IsClonedDLC>
	<StartLongitude d:type="sFloat64" d:alt_encoding="0000000000000000" d:precision="string">0</StartLongitude>
	<StartLatitude d:type="sFloat64" d:alt_encoding="0000000000000000" d:precision="string">0</StartLatitude>
	<StartHeight d:type="sFloat32" d:alt_encoding="0000000000000000" d:precision="string">0</StartHeight>
	<QuickDriveStartName d:type="cDeltaString"></QuickDriveStartName>
	<QuickDriveEndName d:type="cDeltaString"></QuickDriveEndName>
	<QuickDrivePlayerConsistName d:type="cDeltaString"></QuickDrivePlayerConsistName>
</cScenarioProperties>
